clippets/__init__.py
clippets/abc.py
clippets/clippets.css
clippets/colors.py
clippets/core.py
clippets/editor.py
clippets/help.txt
clippets/linux.py
clippets/markup.py
clippets/patches.py
clippets/platform.py
clippets/robot.py
clippets/snippets.py
clippets/tasks.py
clippets/text.py
clippets/widgets.py
clippets/win.py
clippets-0.5.1.dist-info/LICENSE
clippets-0.5.1.dist-info/METADATA
clippets-0.5.1.dist-info/WHEEL
clippets-0.5.1.dist-info/entry_points.txt
clippets-0.5.1.dist-info/top_level.txt
clippets-0.5.1.dist-info/RECORD
