Metadata-Version: 2.1
Name: clippets
Version: 0.5.1
Summary: TUI to build up clipboard content from (rich) text snippets.
Author-email: Paul Ollis <paul@cleversheep.org>
Project-URL: Homepage, https://github.com/paul-ollis/clippets
Project-URL: Bug Tracker, https://github.com/paul-ollis/clippets/issues
Classifier: Development Status :: 4 - Beta
Classifier: License :: OSI Approved :: MIT License
Classifier: Operating System :: Microsoft :: Windows
Classifier: Operating System :: POSIX :: Linux
Classifier: Programming Language :: Python :: 3
Classifier: Environment :: Console
Requires-Python: >=3.9
License-File: LICENSE
Requires-Dist: markdown
Requires-Dist: markdown-strings
Requires-Dist: textual
